backpack/__init__.py
backpack/async_api/__init__.py
backpack/async_api/private/__init__.py
backpack/async_api/private/private.py
backpack/async_api/public/__init__.py
backpack/async_api/public/public.py
backpack/async_api/rest_api.py
backpack/base/__init__.py
backpack/base/models.py
backpack_api-0.0.15.dist-info/LICENSE
backpack_api-0.0.15.dist-info/METADATA
backpack_api-0.0.15.dist-info/WHEEL
backpack_api-0.0.15.dist-info/RECORD
