Metadata-Version: 2.1
Name: backpack-api
Version: 0.0.15
Summary: Backpack REST API python implementation
Author: Web3 Enjoyer
Requires-Python: >=3.9,<4.0
Classifier: Programming Language :: Python :: 3
Classifier: Programming Language :: Python :: 3.9
Classifier: Programming Language :: Python :: 3.10
Classifier: Programming Language :: Python :: 3.11
Requires-Dist: PyNaCl (==1.5.0)
Requires-Dist: aiohttp (==3.9.3)
Requires-Dist: aiohttp-proxy (==0.1.2)
Requires-Dist: cryptography (==42.0.5)
